blueEngine/BETime.py
blueEngine/__init__.py
blueEngine/app.py
blueEngine/blue_object.py
blueEngine/camera.py
blueEngine/canvas.py
blueEngine/component.py
blueEngine/errors.py
blueEngine/font_component.py
blueEngine/game_object.py
blueEngine/gobject.py
blueEngine/input.py
blueEngine/light.py
blueEngine/mesh.py
blueEngine/model.py
blueEngine/scene.py
blueEngine/shader_program.py
blueEngine/textobject.py
blueEngine/texture.py
blueEngine/transfrom.py
blueEngine/utils.py
blueEngine/vao.py
blueEngine/vbo.py
src/blueEngine/__init__.py
src/blueEngine/app.py
src/blueEngine/camera.py
src/blueEngine/component.py
src/blueEngine/errors.py
src/blueEngine/input.py
src/blueEngine/light.py
src/blueEngine/mesh.py
src/blueEngine/model.py
src/blueEngine/scene.py
src/blueEngine/shader_program.py
src/blueEngine/texture.py
src/blueEngine/transfrom.py
src/blueEngine/utils.py
src/blueEngine/vao.py
src/blueEngine/vbo.py
blue_engine-0.0.4.dist-info/METADATA
blue_engine-0.0.4.dist-info/WHEEL
blue_engine-0.0.4.dist-info/license.txt
blue_engine-0.0.4.dist-info/top_level.txt
blue_engine-0.0.4.dist-info/RECORD
