Metadata-Version: 2.1
Name: blue-engine
Version: 0.0.4
Summary: UNKNOWN
Home-page: https://github.com/MrBlueBlobGuy/Blue-Engine
Author: Debojyoti Ganguly
Author-email: debojyotiganguly70@gmail.com
License: MIT
Platform: UNKNOWN
Classifier: License :: OSI Approved :: MIT License
Classifier: Programming Language :: Python :: 3
Classifier: Programming Language :: Python :: 3.10
License-File: license.txt
Requires-Dist: pygame
Requires-Dist: moderngl
Requires-Dist: pyglm
Requires-Dist: numpy
Requires-Dist: noise
Requires-Dist: lupa
